culebrita/__init__.py
culebrita-0.0.1.dist-info/METADATA
culebrita-0.0.1.dist-info/WHEEL
culebrita-0.0.1.dist-info/top_level.txt
culebrita-0.0.1.dist-info/RECORD
