Metadata-Version: 2.1
Name: culebrita
Version: 0.0.1
Summary: Minimalistic and Pythonistic web framework 
Home-page: UNKNOWN
Author: Joseph Mendoza
Author-email: UNKNOWN
License: MIT
Platform: UNKNOWN
